{"series": [{"data": [{"x": "branch_of_albizia_julibrissin", "y": 8.93}, {"x": "branch_of_flowering_cherry", "y": 16.58}, {"x": "branch_of_ginkgo_biloba", "y": 3.7}, {"x": "branch_of_koelreuteria_paniculata", "y": 9.97}, {"x": "branch_of_lagerstroemia_indica", "y": 11.14}, {"x": "branch_of_liriodendron_chinense", "y": 5.21}, {"x": "branch_of_magnolia_liliflora_desr", "y": 6.73}, {"x": "branch_of_platanus", "y": 5.72}, {"x": "branch_of_prunus_cerasifera_f._atropurpurea", "y": 15.34}, {"x": "branch_of_salix_babylonica", "y": 10.63}, {"x": "branch_of_styphnolobium_japonicum", "y": 5.26}, {"x": "branch_of_triadica_sebifera", "y": 6.35}, {"x": "branch_of_zelkova_serrata", "y": 10.08}]}], "options": {"chart": {"type": "treemap", "height": 540}, "legend": {"show": false}, "plotOptions": {"treemap": {"distributed": true, "enableShades": false}}, "title": {"text": "Average area of class objects on image", "align": "left"}, "colors": ["#800000", "#008000", "#808000", "#000080", "#800080", "#008080", "#808080", "#400000", "#c00000", "#408000", "#c08000", "#400080", "#c00080"], "tooltip": {"y": {}}}, "type": "treemap", "height": 350, "sly_options": {"tooltip": "Average area of class objects on image is {y}%"}}